README.txt
bootstrap.py
buildout.cfg
setup.cfg
setup.py
collective/__init__.py
collective.zrtresource.egg-info/PKG-INFO
collective.zrtresource.egg-info/SOURCES.txt
collective.zrtresource.egg-info/dependency_links.txt
collective.zrtresource.egg-info/entry_points.txt
collective.zrtresource.egg-info/namespace_packages.txt
collective.zrtresource.egg-info/not-zip-safe
collective.zrtresource.egg-info/requires.txt
collective.zrtresource.egg-info/top_level.txt
collective/zrtresource/README.txt
collective/zrtresource/__init__.py
collective/zrtresource/configure.zcml
collective/zrtresource/tests.py
collective/zrtresource/zcml.txt
collective/zrtresource/zrtresource.py
docs/HISTORY.txt