Metadata-Version: 1.0
Name: collective.zrtresource
Version: 0.1
Summary: This package is a tiny wrapper around z3c.zrtresource so it works in Zope2 (tested with 2.10).
Home-page: UNKNOWN
Author: Tim Terlegard, JC Brand
Author-email: jc@opkode.com
License: GPL
Keywords: plone zrtresource
Platform: UNKNOWN
Classifier: Programming Language :: Python
Classifier: Topic :: Software Development :: Libraries :: Python Modules
